tuvi_mcp-1.0.1.dist-info/METADATA
tuvi_mcp-1.0.1.dist-info/WHEEL
tuvi_mcp-1.0.1.dist-info/entry_points.txt
tuvi_mcp/__init__.py
tuvi_mcp/libs/__init__.py
tuvi_mcp/libs/can_chi.py
tuvi_mcp/libs/khuyen.py
tuvi_mcp/libs/lunar_date.py
tuvi_mcp/libs/xung_khac.py
tuvi_mcp/server.py
tuvi_mcp-1.0.1.dist-info/RECORD
