Metadata-Version: 2.1
Name: tuvi-mcp
Version: 1.0.1
Summary: MCP Server for Vietnamese Fortune Telling based on Lunar Calendar
Keywords: mcp,fortune-telling,vietnamese,lunar-calendar,tu-vi,can-chi,ngu-hanh
Author-Email: Mao Bui <maonguyen199873@gmail.com>
Maintainer-Email: Mao Bui <maonguyen199873@gmail.com>
License: MIT
Classifier: Development Status :: 4 - Beta
Classifier: Intended Audience :: Developers
Classifier: License :: OSI Approved :: MIT License
Classifier: Operating System :: OS Independent
Classifier: Programming Language :: Python :: 3
Classifier: Programming Language :: Python :: 3.12
Classifier: Programming Language :: Python :: 3.13
Classifier: Topic :: Software Development :: Libraries :: Python Modules
Classifier: Topic :: Scientific/Engineering :: Astronomy
Project-URL: Homepage, https://github.com/MaoBui2907/tuvi-mcp
Project-URL: Repository, https://github.com/MaoBui2907/tuvi-mcp
Project-URL: Issues, https://github.com/MaoBui2907/tuvi-mcp/issues
Project-URL: Changelog, https://github.com/MaoBui2907/tuvi-mcp/blob/main/README.md
Requires-Python: >=3.12
Requires-Dist: fastmcp>=2.14.1
Requires-Dist: lunardate>=0.2.2
Requires-Dist: lunar-python>=1.4.8
